{"folders": ["master", "v4.9.0", "v5.0.0", "v5.1.0", "v5.2.0", "v6.0.0", "v6.1.0", "v6.2.0", "v6.3.0", "v7.0.0", "v7.0.1", "v7.1.0", "v7.2.0", "v7.3.0"], "default-branch": "master", "labels": {"master": "master", "v4.9.0": "v4.9.0", "v5.0.0": "v5.0.0", "v5.1.0": "v5.1.0", "v5.2.0": "v5.2.0", "v6.0.0": "v6.0.0", "v6.1.0": "v6.1.0", "v6.2.0": "v6.2.0", "v6.3.0": "v6.3.0", "v7.0.0": "v7.0.0", "v7.0.1": "v7.0.1", "v7.1.0": "v7.1.0", "v7.2.0": "v7.2.0", "v7.3.0": "v7.3.0 (latest)"}, "versions": ["master", "v7.3.0", "v7.2.0", "v7.1.0", "v7.0.1", "v7.0.0", "v6.3.0", "v6.2.0", "v6.1.0", "v6.0.0", "v5.2.0", "v5.1.0", "v5.0.0", "v4.9.0"], "warnings": {"master": ["unreleased"], "v4.9.0": ["outdated"], "v5.0.0": ["outdated"], "v5.1.0": ["outdated"], "v5.2.0": ["outdated"], "v6.0.0": ["outdated"], "v6.1.0": ["outdated"], "v6.2.0": ["outdated"], "v6.3.0": ["outdated"], "v7.0.0": ["outdated"], "v7.0.1": ["outdated"], "v7.1.0": ["outdated"], "v7.2.0": ["outdated"], "v7.3.0": []}, "latest": "v7.3.0", "downloads": {"master": [], "v4.9.0": [], "v5.0.0": [], "v5.1.0": [], "v5.2.0": [], "v6.0.0": [], "v6.1.0": [], "v6.2.0": [], "v6.3.0": [], "v7.0.0": [], "v7.0.1": [], "v7.1.0": [], "v7.2.0": [], "v7.3.0": []}}